{
    "room": "StoryLife.lt",
    "author": "by breznevasmn",
    "icon": "null
    "css": "https://cdn.bssecure.net/nc-themes/plug-themes/nc331-theme.css",
    "rules": {
        "allowAutorespond": true,
        "allowAutowoot": true,
        "allowAutojoin": true,
        "allowAutograb": true,
        "allowSmartVote": true,
        "allowEmotes": true,
        "allowShowingMehs": true,
        "forceSmartVote": false
    },
    "ccc": {
        "admin": "#42A5DC",
        "ambassador": "#84B423",
        "host": #87449c,
        "cohost": "#F3508F",
        "manager": "#F3508F",
        "bouncer": "#F3508F",
        "rdj": "#5DB4FF",
        "subscriber": "#A1A6B3",
        "silversubscriber": "#A1A6B3",
        "friend": "#B35D88",
        "user": "#8B92A3"
    },
    "images": {
        "background": "http://www.part.lt/img/cfbcdd0d22add00997fce79d68255c14406.jpg"
        "playback": null,
        "admin": "https://cdn.bssecure.net/nc-themes/img/adGS_Ranks_Admin.png",
        "ambassador": "https://cdn.bssecure.net/nc-themes/img/adGS_Ranks_BA.png",
        "host":  "https://cdn.bssecure.net/nc-themes/img/adGS_Ranks_Host.png",
        "cohost": "https://cdn.bssecure.net/nc-themes/img/adGS_Ranks_CoHost.png",
        "manager": "https://cdn.bssecure.net/nc-themes/img/adGS_Ranks_Manager.png",
        "bouncer": "https://cdn.bssecure.net/nc-themes/img/adGS_Ranks_Bouncer.png",
        "rdj": "https://cdn.bssecure.net/nc-themes/img/adGS_Ranks_RDJ.png",
        "subscriber": null,
        "silversubscriber": "https://cdn.radiant.dj/rcs/icons/radiant/subscriber.png"
    },
    "autocomplete": {
        "!gb": 2,
        "!getban": 2,
        "!clearchat": 2,
        "!cl": 2,
        "!chatlevel": 2,
        "!b": 2,
        "!ban": 2,
        "!a": 2,
        "!add": 2,
        "!c": 2,
        "!cycle": 2,
        "!l": 2,
        "!clearlock": 2,
        "!d": 2,
        "!deletechat": 2,
        "!lock": 2,
        "!k": 2,
        "!kick": 2,
        "!getcid": 2,
        "!getid": 2,
        "!ls": 2,
        "!lockskip": 2,
        "!lockdown": 2,
        "!m": 2,
        "!move": 2,
        "!stats": 2,
        "!status": 2,
        "!test": 2,
        "!mute": 2,
        "!rw": 2,
        "!resetwarn": 2,
        "!resetwarnings": 2,
        "!s": 2,
        "!skip": 2,
        "!lb": 2,
        "!t": 2,
        "!toggle": 2,
        "!settings": 2,
        "!swap": 2,
        "!r": 2,
        "!remove": 2,
        "!spin": 2,
        "!ul": 2,
        "!unlock": 2,
        "!ub": 2,
        "!unban": 2,
        "!avatar": 3,
        "!whois": 2,
        "!w": 2,
        "!warn": 2,
        "!um": 2,
        "!unmute": 2,
        "!uptime": 2,
        "!permit": 2,
        "!reload": 2,
        "!badge": 3,
        "!allcommands": 100,
        "!die": 100,
        "!version": 100,
        "!afk": 0,
        "!su": 100,
        "!unsu": 100,
        "!afkinfo": 0,
        "!blacklist": 0,
        "!alist": 0,
        "!oplist": 0,
        "!nsfwlist": 0,
        "!eng": 2,
        "!english": 2,
        "!cmd": 0,
        "!commands": 0,
        "!donate": 0,
        "!fb": 0,
        "!facebook": 0,
        "!dc": 0,
        "!dclookup": 0,
        "!disconnected": 0,
        "!event": 0,
        "!events": 0,
        "!fbg": 0,
        "!facebookgroup": 0,
        "!fbgroup": 0,
        "!group": 0,
        "!kms": 0,
        "!killmyself": 0,
        "!mystats": 0,
        "!me": 0,
        "!image": 0,
        "!thumb": 0,
        "!getmedia": 0,
        "!ping": 0,
        "!help": 0,
        "!link": 0,
        "!rcs": 0,
        "!p3": 0,
        "!plugcubed": 0,
        "!p0": 0,
        "!p0ne": 0,
        "!tastyplug": 0,
        "!tp": 0,
        "!origem": 0,
        "!origemwoot": 0,
        "!plugable": 0,
        "!reward": 0,
        "!buy": 0,
        "!purchase": 0,
        "!cmpr": 0,
        "!rmr": 0,
        "!rewards": 0,
        "!motd": 0,
        "!rce": 0,
        "!chromeextension": 0,
        "!rm": 0,
        "!monies": 0,
        "!radiantpoints": 0,
        "!points": 0,
        "!mymoney": 0,
        "!money": 0,
        "!coins": 0,
        "!rp": 0,
        "!cmp": 0,
        "!communitypoints": 0,
        "!steam": 0,
        "!slack": 0,
        "!community": 0,
        "!slots": 0,
        "!staff": 0,
        "!shop": 0,
        "!ts": 0,
        "!teamspeak": 0,
        "!tw": 0,
        "!twitter": 0,
        "!theme": 0,
        "!urban": 0,
        "!ud": 0,
        "!users": 0,
        "!ustats": 0,
        "!weather": 0,
        "!fweather": 0,
        "!yt": 0,
        "!youtube": 0,
        "!web": 0,
        "!website": 0,
        "!radiant": 0,
        "!demotivate": 0,
        "!demotivation": 0,
        "!cookie": 0,
        "!bacon": 0,
        "!whoami": 0,
        "!giveafuck": 0,
        "!givefuck": 0,
        "!fucks": 0,
        "!gaf": 0,
        "!stockfucks": 0,
        "!sf": 0,
        "!location": 0,
        "!pie": 0,
        "!insult": 0,
        "!motivate": 0,
        "!motivation": 0,
        "!flirt": 0,
        "!pringles": 0,
        "!shh": 0,
        "!meh": 0,
        "!thisisfine": 0,
        "!tif": 0,
        "!snail": 0,
        "!snailislove": 0,
        "!snailislife": 0,
        "!stfu": 0,
        "!taco": 0,
        "!tmyk": 0,
        "!triggered": 0,
        "!trigger": 0,
        "!tr": 0,
        "!treat": 0,
        "!roulette": 2,
        "!wlroulette": 2,
        "!kickroulette": 2,
        "!fixroulette": 2,
        "!play": 0,
        "!wlbuddy": 2,
        "!join": 0,
        "!leave": 0,
        "!plug": 0,
        "!rule": 0,
        "!op": 2,
        "!awful": 2,
        "!nsfw": 2,
        "!say": 2,
        "!team": 0,
        "!gift": 0,
        "!giftrm": 0,
        "!giftrp": 0,
        "!removebl": 2,
        "!surp": 100,
        "!surm": 100,
        "!about": 0,
        "!aboutlb": 0,
        "!eta": 0,
        "!sc": 0,
        "!snap": 0,
        "!snapchat": 0,
        "!rules": 0,
        "!guidelines": 0,
        "!counters": 100,
        "!slotscounters": 100,
        "!aboutv2": 0,
        "!aboutlbv2": 0,
        "!visit": 100,
        "!traitor": 100,
        "!opcheck": 2,
        "!opc": 2,
        "!hyaps": 0,
        "!dazzuhpls": 0,
        "!dazzuh": 0,
        "!staffapp": 0,
        "!pp": 100
    },
    "emotes": {
 "firelenny":                    "https://i.imgur.com/jleilmo.gif",
        "pusheennoodles":               "http://fc07.deviantart.net/fs71/f/2014/359/e/5/pusheen_eating_ramen_by_pikuniku-d8b5irh.gif",
        "pusheencookies":               "http://orig02.deviantart.net/956e/f/2014/201/6/9/_free_avatar__chef_pusheen_by_jericam-d7rhjnt.gif",
        "rainbowsheep":                 "http://fc09.deviantart.net/fs71/f/2015/035/1/b/rainbow_sheep_by_addmedia-d8gpqbw.gif",
        "twerk":                        "https://i.imgur.com/kF7m9Ab.gif",
        "banned":                       "https://i.imgur.com/EOuLASw.gif",
        "kawaiighost":                  "https://i.imgur.com/TC6h5uy.gif",
        "rainbowllama":                 "https://i.imgur.com/2xQpOh6.gif",
        "nat":                          "https://i.imgur.com/ZbRznPp.gif",
        "d2rage":                       "http://hydra-media.cursecdn.com/dota2.gamepedia.com/e/e4/Emoticon_rage.gif?version=6887e870be370c1439ea8cf58e0d0a3a",
        "d2salty":                      "http://hydra-media.cursecdn.com/dota2.gamepedia.com/7/7a/Emoticon_salty.gif?version=0c2f6756952b7c29ed0adc0d17b4c5a2",
        "d2cry":                        "http://hydra-media.cursecdn.com/dota2.gamepedia.com/5/5b/Emoticon_tears.gif?version=c8678e5807a8c8ff6dadf38c9f8338f5",
        "d2surprise":                   "http://hydra-media.cursecdn.com/dota2.gamepedia.com/d/d9/Emoticon_surprise.gif?version=395640aa022368f92485cd252722128b",
        "d2horse":                      "http://hydra-media.cursecdn.com/dota2.gamepedia.com/f/f7/Emoticon_horse.gif?version=81e77e5a46b5b6388ccb017682af6664",
        "papaya":                       "https://i.imgur.com/CygrZK8.png",
        "oops":                         "https://i.imgur.com/AwCW1f1.png",
        "4ninja":                       "https://i.imgur.com/GGtRmcy.gif",
        "4neko":                        "https://i.imgur.com/2NSEZr3.gif",
        "4play":                        "https://i.imgur.com/8qIYB9k.gif",
        "res":                          "https://i.imgur.com/RTAafmV.jpg",
        "umaru":                        "https://i.imgur.com/u9wayzx.png",
        "pantsu":                       "https://i.imgur.com/pFbtK5l.png",
        "tuturu":                       "https://i.imgur.com/2aSciA1.png",
        "trgsfear":                     "https://i.imgur.com/S6e9uNV.jpg",
        "petme":                        "https://i.imgur.com/ZcXheej.gif",
        "sadneko":                      "https://i.imgur.com/fDPfNZd.gif",
        "lelneko":                      "https://i.imgur.com/7DKtJau.gif",
        "bugdj":                        "https://i.imgur.com/O3m7Lny.png",
        "lennygif":                     "https://i.imgur.com/Rii79kX.gif",
        "isla":                         "https://i.imgur.com/CTL9knY.png",
        "kabum":                        "https://cdn.bssecure.net/nightcore/emotes/kabum.png",
        "pillowgirl":                   "https://cdn.bssecure.net/nightcore/emotes/pillowgirl.gif",
        "allokitty":                    "https://i.imgur.com/j7EemL2.png",
        "nekopraise":                   "https://i.imgur.com/bafHllY.gif",
        "nekospin":                     "https://i.imgur.com/ikekvtQ.gif",
        "pusheensleep":                 "https://i.imgur.com/j1pEPMP.gif",
        "emishush":                     "https://i.imgur.com/MSHrwTZ.gif",
        "emiconfused":                  "https://i.imgur.com/hDoGSZ5.gif",
        "2scary":                       "https://cdn.bssecure.net/nightcore/2scary.png",
        "sadmikh":                      "https://cdn.bssecure.net/nightcore/sadmikh.png",
        "harambe":                      "https://i.imgur.com/zGwRv1t.png",
        "harambeking":                  "https://i.imgur.com/hy9zRYz.png",
        "triggered":                    "https://i.imgur.com/XPgBvC7.gif",
        "pinguh":                       "http://cdn.frankerfacez.com/558d8587e1e81bb8cff660b77ccd22cd.PNG",
        "wew":                          "https://i.imgur.com/i5B5LSI.png",
        "chucklul":                     "https://i.imgur.com/jDPUezw.png",
        "boi":                          "https://i.imgur.com/YnIpiMu.png",
        "emishrug":                     "https://i.imgur.com/omwfW0G.png",
        "jizzface":                     "https://i.imgur.com/ZgAj3PO.png",
        "hitagi":                       "https://i.imgur.com/edDtIpA.png",
        "luldva":                       "https://cdn.bssecure.net/img/plug/luldva.png",
        "lulnoon":                      "https://cdn.bssecure.net/img/plug/lulnoon.png",
        "lulzarya":                     "https://cdn.bssecure.net/img/plug/lulzarya.png",
        "k":                            "https://i.imgur.com/s6r1L8S.png",
        "feelsbanman":                  "https://cdn.bssecure.net/img/plug/feelsbanman.png",
        "ermahgawd":                    "https://i.imgur.com/6aRkzqa.jpg",
        "rollingeyes":                  "https://i.imgur.com/Li3hhCc.png",
        "feelsryuugawagatekiwokurau":   "https://i.imgur.com/mYvYbMN.png",
        "notlikemiya":                  "https://i.imgur.com/mz6m2ne.png"
    }
}